tap_ex1/__init__.py
tap_ex1/__main__.py
tap_ex1/client.py
tap_ex1/schemas/__init__.py
tap_ex1/streams.py
tap_ex1/tap.py
tap_ex1-0.0.1.dist-info/LICENSE
tap_ex1-0.0.1.dist-info/METADATA
tap_ex1-0.0.1.dist-info/WHEEL
tap_ex1-0.0.1.dist-info/entry_points.txt
tap_ex1-0.0.1.dist-info/RECORD
